{"title":"인기 초등학생책가방 추천 Top 10","description":"초등학생책가방 정보가 궁금하신가요? 종류가 너무 많아서 도대체 어떤 제품을 구매해야할지 고민이시죠?\n실시간 통계를 바탕으로 사용자들에게 많은 사랑을 받고 있는 제품들을 소개해드립니다.\n추천드린 제품들을 꼼꼼히 비교해보시고 합리적인 소비하시길 바랍니다!","date":"2022-02-28 22:00:01","category":"","products":[{"productId":6256754092,"productName":"베네통키즈 아동용 레인보우 스팽글 책가방 세트 QCBGP3211PK","productPrice":57150,"productImage":"https://static.coupangcdn.com/image/retail/images/10766903033143526-444b4e43-94e2-4ea4-acde-681753ab2f9a.jpg","productUrl":"https://link.coupang.com/re/AFFSDP?lptag=AF3097610&pageKey=6256754092&itemId=12716079980&vendorItemId=79982841937&traceid=V0-153-3176d93af2a554df","keyword":"초등학생책가방","rank":1,"isRocket":true,"isFreeShipping":false},{"productId":4731431598,"productName":"베네통키즈 하트포켓 글리터비즈 책가방 세트 QCBGP2111MU","productPrice":77150,"productImage":"https://static.coupangcdn.com/image/rs_quotation_api/esgfynep/96f213cceae84684ada046bef02d1fa3.jpg","productUrl":"https://link.coupang.com/re/AFFSDP?lptag=AF3097610&pageKey=4731431598&itemId=5997543737&vendorItemId=73093380696&traceid=V0-153-993f424b34645dae","keyword":"초등학생책가방","rank":2,"isRocket":true,"isFreeShipping":false},{"productId":249894320,"productName":"마블 스파이더맨 모디쉬 책가방 세트 MV0386","productPrice":49800,"productImage":"https://static.coupangcdn.com/image/retail/images/2019/07/02/11/4/ad8e0b18-fb42-443f-83ca-5f867c208866.jpg","productUrl":"https://link.coupang.com/re/AFFSDP?lptag=AF3097610&pageKey=249894320&itemId=789941320&vendorItemId=5004023635&traceid=V0-153-97059c52350e84ac","keyword":"초등학생책가방","rank":3,"isRocket":true,"isFreeShipping":false},{"productId":249894339,"productName":"마블 캡틴 모디쉬 책가방 세트 MV0384","productPrice":59240,"productImage":"https://static.coupangcdn.com/image/retail/images/2019/07/02/11/6/4cf55868-9b26-4cc0-9484-f79848fdbe0c.jpg","productUrl":"https://link.coupang.com/re/AFFSDP?lptag=AF3097610&pageKey=249894339&itemId=789941377&vendorItemId=5004023739&traceid=V0-153-472a13718d66caef","keyword":"초등학생책가방","rank":4,"isRocket":true,"isFreeShipping":false},{"productId":6291160153,"productName":"나이키 브라질리아 18리터 책가방 백팩 + 책갈피볼펜","productPrice":59800,"productImage":"https://static.coupangcdn.com/image/vendor_inventory/120b/b586b2e4fcf0d3466f04701c3985165f9b4cff20bf35c646d86c81e48ca2.jpg","productUrl":"https://link.coupang.com/re/AFFSDP?lptag=AF3097610&pageKey=6291160153&itemId=12963195196&vendorItemId=80227323621&traceid=V0-153-f70f6f8d67942705","keyword":"초등학생책가방","rank":5,"isRocket":true,"isFreeShipping":false},{"productId":165319619,"productName":"윙하우스 윙 체크 엠보 책가방세트 WH0467","productPrice":32820,"productImage":"https://static.coupangcdn.com/image/retail/images/2019/02/01/12/8/5034a575-b2f7-4984-b48e-8fef557bf9b1.jpg","productUrl":"https://link.coupang.com/re/AFFSDP?lptag=AF3097610&pageKey=165319619&itemId=474128992&vendorItemId=4350641533&traceid=V0-153-992fdeb191fef5ea","keyword":"초등학생책가방","rank":6,"isRocket":true,"isFreeShipping":false},{"productId":6269612581,"productName":"어몽어스 남아용 커터 책가방세트 PO208","productPrice":113050,"productImage":"https://static.coupangcdn.com/image/rs_quotation_api/hpykq4dq/42f4edaf401d4c6aac43d654f0846e1a.jpg","productUrl":"https://link.coupang.com/re/AFFSDP?lptag=AF3097610&pageKey=6269612581&itemId=12814154719&vendorItemId=80589163941&traceid=V0-153-1f3bbe69580de154","keyword":"초등학생책가방","rank":7,"isRocket":false,"isFreeShipping":true},{"productId":4590498613,"productName":"빅토리아앤프렌즈 에코사첼 책가방 2종 세트","productPrice":114370,"productImage":"https://static.coupangcdn.com/image/retail/images/2020/12/11/15/9/371b60a1-4626-4bcb-a89c-90ba817810a3.jpg","productUrl":"https://link.coupang.com/re/AFFSDP?lptag=AF3097610&pageKey=4590498613&itemId=5643402077&vendorItemId=72942414606&traceid=V0-153-694925cef950953d","keyword":"초등학생책가방","rank":8,"isRocket":true,"isFreeShipping":false},{"productId":2040410067,"productName":"빅토리아앤프렌즈 책가방 2종 세트 얼쓰에코 + 더스트백","productPrice":101300,"productImage":"https://static.coupangcdn.com/image/retail/images/4196916659646254-c424306f-72e0-45fb-b6af-59db0a973d90.jpg","productUrl":"https://link.coupang.com/re/AFFSDP?lptag=AF3097610&pageKey=2040410067&itemId=3468875700&vendorItemId=71455221178&traceid=V0-153-f3206910c34b4ed4","keyword":"초등학생책가방","rank":9,"isRocket":true,"isFreeShipping":false},{"productId":6346790303,"productName":"DFMEI 모리 단색 모든 일치 중학교 학생 한국어 스타일 배낭 여성 배낭 대학생","productPrice":51660,"productImage":"https://static.coupangcdn.com/image/vendor_inventory/3c98/5e7fcf16617e06974d73233aab400d7c15a09c7057fe617c7910d0780d71.jpg","productUrl":"https://link.coupang.com/re/AFFSDP?lptag=AF3097610&pageKey=6346790303&itemId=13338720449&vendorItemId=80594045153&traceid=V0-153-352661f8b1182014","keyword":"초등학생책가방","rank":10,"isRocket":false,"isFreeShipping":true}],"keyword":"초등학생책가방"}